app_creator/__init__.py
app_creator/__main__.py
app_creator/core.py
melodie_app_django_creator_smart-0.1.0.dist-info/licenses/LICENSE
myapp/__init__.py
myapp/admin.py
myapp/apps.py
myapp/models.py
myapp/urls.py
myapp/views.py
melodie_app_django_creator_smart-0.1.0.dist-info/METADATA
melodie_app_django_creator_smart-0.1.0.dist-info/WHEEL
melodie_app_django_creator_smart-0.1.0.dist-info/entry_points.txt
melodie_app_django_creator_smart-0.1.0.dist-info/top_level.txt
melodie_app_django_creator_smart-0.1.0.dist-info/RECORD
